{
  
"version": 40,
"message": "อัพเดทล่าสุด 04/03/2026 1:16น. \nConfig Version: 40 \n \แก้ไข้แอพใหม่ \n \nรองรับการใช้งาน OpenVPN SSH SSL SlowDNS V2rey UDP \n \n🔴 True \n🔵 Dtac \n🟢 Als \n \nรีวิวให้ 5 ดาวแอพฯของเราบน \nGoogle Play ด้วยน่ะครับ ⭐⭐⭐⭐⭐",

"fileUrl": "https://i-have.xyz/config/ihavevpn.json",

"messageWarning":"มีการอัพเดทระบบดังต่อไปนี้?\n• อัพเดทระบบ UI \n• แก้ไขระบบเซิร์ฟเวอร์ \n• แก้ไขบัคในแอพ \n ขอบคุณสำหรับความเข้าใจของคุณ ❤️",
"title":"ไม่สามารถใช้เวอร์ชันปัจจุบันต่อได้ คุณต้องทำการอัพเกรด V1.0.7 ",
"link":"https://play.google.com/store/apps/details?id=ihave.pro.net",
"website":"https://play.google.com/store/apps/details?id=ihave.pro.net",
"versionCode": 7
  
}
